performance_profiler/__init__.py
performance_profiler/bottleneck_detector.py
performance_profiler/comparator.py
performance_profiler/historical_tracker.py
performance_profiler/line_profiler.py
performance_profiler/memory_profiler.py
performance_profiler/optimizer.py
performance_profiler/profiler.py
performance_profiler_optimizer-1.0.0.dist-info/licenses/LICENSE
performance_profiler_optimizer-1.0.0.dist-info/METADATA
performance_profiler_optimizer-1.0.0.dist-info/WHEEL
performance_profiler_optimizer-1.0.0.dist-info/top_level.txt
performance_profiler_optimizer-1.0.0.dist-info/RECORD
