Metadata-Version: 2.4
Name: performance-profiler-optimizer
Version: 1.0.0
Summary: Comprehensive Python profiling toolkit with memory tracking, bottleneck detection, and historical analysis
Home-page: https://github.com/yourusername/performance-profiler-optimizer
Author: Performance Optimizer Team
Author-email: Garuba Malik <garubamalik@gmail.com>
License: MIT
Project-URL: Homepage, https://github.com/officialgabzz/memory_profiler_optimiser
Project-URL: Documentation, https://github.com/officialgabzz/memory_profiler_optimiser#readme
Project-URL: Repository, https://github.com/officialgabzz/memory_profiler_optimiser
Project-URL: Issues, https://github.com/officialgabzz/memory_profiler_optimiser/issues
Project-URL: Changelog, https://github.com/officialgabzz/memory_profiler_optimiser/blob/master/CHANGELOG.md
Keywords: performance,profiling,optimization,memory,bottleneck,tracking,monitoring,profiler,analyzer
Classifier: Development Status :: 5 - Production/Stable
Classifier: Intended Audience :: Developers
Classifier: Topic :: Software Development :: Testing
Classifier: Topic :: System :: Monitoring
Classifier: License :: OSI Approved :: MIT License
Classifier: Programming Language :: Python :: 3
Classifier: Programming Language :: Python :: 3.7
Classifier: Programming Language :: Python :: 3.8
Classifier: Programming Language :: Python :: 3.9
Classifier: Programming Language :: Python :: 3.10
Classifier: Programming Language :: Python :: 3.11
Classifier: Operating System :: OS Independent
Requires-Python: >=3.7
License-File: LICENSE
Requires-Dist: psutil>=5.8.0
Provides-Extra: dev
Requires-Dist: pytest>=7.0.0; extra == "dev"
Requires-Dist: pytest-cov>=3.0.0; extra == "dev"
Requires-Dist: black>=22.0.0; extra == "dev"
Requires-Dist: flake8>=4.0.0; extra == "dev"
Dynamic: author
Dynamic: home-page
Dynamic: license-file
Dynamic: requires-python
